famafrench/__init__.py
famafrench/famafrench.py
famafrench/utils.py
famafrench/version.py
famafrench/wrdsconnect.py
famafrench-0.1.4.dist-info/LICENSE.txt
famafrench-0.1.4.dist-info/METADATA
famafrench-0.1.4.dist-info/WHEEL
famafrench-0.1.4.dist-info/top_level.txt
famafrench-0.1.4.dist-info/RECORD
